matrixmultiply/__init__.py
matrixmultiply/multiply.py
matrixmultiply-0.1.0.dist-info/METADATA
matrixmultiply-0.1.0.dist-info/WHEEL
matrixmultiply-0.1.0.dist-info/top_level.txt
matrixmultiply-0.1.0.dist-info/RECORD
